scraper/Scraper.py
scraper/__init__.py
peviitor_pyscraper-0.0.5.dist-info/LICENSE
peviitor_pyscraper-0.0.5.dist-info/METADATA
peviitor_pyscraper-0.0.5.dist-info/WHEEL
peviitor_pyscraper-0.0.5.dist-info/top_level.txt
peviitor_pyscraper-0.0.5.dist-info/RECORD
